{
  "1479553527222239275": {
    "1462308991160942675": {
      "xp": 0,
      "level": 2,
      "total_xp": 100
    },
    "1019698414839156817": {
      "xp": 239,
      "level": 4,
      "total_xp": 1140
    },
    "1365071801201463330": {
      "xp": 388,
      "level": 3,
      "total_xp": 770
    },
    "1104513917595680769": {
      "xp": 10,
      "level": 1,
      "total_xp": 10
    },
    "1457507909692035181": {
      "xp": 10,
      "level": 1,
      "total_xp": 10
    },
    "1437205774853214270": {
      "xp": 20,
      "level": 1,
      "total_xp": 20
    },
    "1261882573039206401": {
      "xp": 60,
      "level": 1,
      "total_xp": 60
    },
    "1079826643922722848": {
      "xp": 80,
      "level": 1,
      "total_xp": 80
    },
    "1314412618219520041": {
      "xp": 10,
      "level": 1,
      "total_xp": 10
    },
    "1141232275447631932": {
      "xp": 40,
      "level": 2,
      "total_xp": 140
    },
    "1425265292094738686": {
      "xp": 10,
      "level": 1,
      "total_xp": 10
    },
    "814828868606885939": {
      "xp": 20,
      "level": 1,
      "total_xp": 20
    },
    "1448123679396331694": {
      "xp": 10,
      "level": 1,
      "total_xp": 10
    },
    "1409125312767463527": {
      "xp": 20,
      "level": 1,
      "total_xp": 20
    }
  },
  "1345393622895300672": {
    "1246921829818306590": {
      "xp": 1341,
      "level": 6,
      "total_xp": 4160
    },
    "1327038072306798642": {
      "xp": 28,
      "level": 9,
      "total_xp": 8430
    },
    "1314412618219520041": {
      "xp": 470,
      "level": 8,
      "total_xp": 6610
    },
    "1427762248994263104": {
      "xp": 991,
      "level": 6,
      "total_xp": 3810
    },
    "1276974534985121832": {
      "xp": 340,
      "level": 8,
      "total_xp": 6480
    },
    "1445433326671237231": {
      "xp": 190,
      "level": 2,
      "total_xp": 290
    },
    "1019698414839156817": {
      "xp": 160,
      "level": 2,
      "total_xp": 260
    },
    "1162228493048889395": {
      "xp": 199,
      "level": 5,
      "total_xp": 1900
    },
    "1225523235366506627": {
      "xp": 1550,
      "level": 8,
      "total_xp": 7690
    },
    "1379610143880253570": {
      "xp": 60,
      "level": 1,
      "total_xp": 60
    },
    "1441854804090683535": {
      "xp": 60,
      "level": 2,
      "total_xp": 160
    },
    "1442974183448510617": {
      "xp": 30,
      "level": 2,
      "total_xp": 130
    },
    "1434260488585478207": {
      "xp": 89,
      "level": 4,
      "total_xp": 990
    },
    "1402071741332721786": {
      "xp": 20,
      "level": 1,
      "total_xp": 20
    },
    "1284601939081953290": {
      "xp": 20,
      "level": 2,
      "total_xp": 120
    },
    "1246931401954164748": {
      "xp": 78,
      "level": 3,
      "total_xp": 460
    },
    "1422383486207004854": {
      "xp": 10,
      "level": 2,
      "total_xp": 110
    },
    "1430338222315012099": {
      "xp": 199,
      "level": 4,
      "total_xp": 1100
    },
    "1298078354431283253": {
      "xp": 30,
      "level": 1,
      "total_xp": 30
    },
    "1314808467675938877": {
      "xp": 40,
      "level": 1,
      "total_xp": 40
    },
    "1253054253820547092": {
      "xp": 40,
      "level": 1,
      "total_xp": 40
    },
    "918009071955746838": {
      "xp": 40,
      "level": 1,
      "total_xp": 40
    }
  },
  "1276298012393607231": {
    "1019698414839156817": {
      "xp": 1490,
      "level": 8,
      "total_xp": 7630
    },
    "1141232275447631932": {
      "xp": 3326,
      "level": 11,
      "total_xp": 17590
    },
    "1365071801201463330": {
      "xp": 111,
      "level": 6,
      "total_xp": 2930
    },
    "1462308991160942675": {
      "xp": 40,
      "level": 1,
      "total_xp": 40
    },
    "1396440832701239316": {
      "xp": 70,
      "level": 2,
      "total_xp": 170
    },
    "1357934205245460521": {
      "xp": 248,
      "level": 3,
      "total_xp": 630
    },
    "1167619916669661185": {
      "xp": 408,
      "level": 3,
      "total_xp": 790
    },
    "1391231433498038405": {
      "xp": 50,
      "level": 2,
      "total_xp": 150
    },
    "1397973722606076027": {
      "xp": 100,
      "level": 2,
      "total_xp": 200
    },
    "333198595018719232": {
      "xp": 59,
      "level": 4,
      "total_xp": 960
    },
    "1476564133095931988": {
      "xp": 70,
      "level": 1,
      "total_xp": 70
    },
    "1211855491299414056": {
      "xp": 160,
      "level": 2,
      "total_xp": 260
    },
    "1458608830324674625": {
      "xp": 40,
      "level": 1,
      "total_xp": 40
    },
    "1459090459023507603": {
      "xp": 98,
      "level": 3,
      "total_xp": 480
    },
    "475505232957407252": {
      "xp": 110,
      "level": 2,
      "total_xp": 210
    },
    "1437205774853214270": {
      "xp": 139,
      "level": 4,
      "total_xp": 1040
    },
    "1202514242692063255": {
      "xp": 270,
      "level": 2,
      "total_xp": 370
    },
    "1213138733621190706": {
      "xp": 60,
      "level": 1,
      "total_xp": 60
    },
    "1377784236400050249": {
      "xp": 10,
      "level": 1,
      "total_xp": 10
    },
    "1363350212252270712": {
      "xp": 10,
      "level": 1,
      "total_xp": 10
    },
    "1493789953912733757": {
      "xp": 38,
      "level": 3,
      "total_xp": 420
    },
    "1493100535392374994": {
      "xp": 279,
      "level": 5,
      "total_xp": 1980
    },
    "1425265292094738686": {
      "xp": 1402,
      "level": 7,
      "total_xp": 5690
    },
    "1396734690391490590": {
      "xp": 90,
      "level": 1,
      "total_xp": 90
    },
    "1258840909764755489": {
      "xp": 240,
      "level": 2,
      "total_xp": 340
    },
    "1491920254979276841": {
      "xp": 200,
      "level": 2,
      "total_xp": 300
    },
    "1407004790684389550": {
      "xp": 60,
      "level": 1,
      "total_xp": 60
    },
    "432650303385370627": {
      "xp": 80,
      "level": 1,
      "total_xp": 80
    },
    "1448123679396331694": {
      "xp": 109,
      "level": 4,
      "total_xp": 1010
    },
    "1122275886033551361": {
      "xp": 80,
      "level": 2,
      "total_xp": 180
    },
    "1253289820508262560": {
      "xp": 138,
      "level": 3,
      "total_xp": 520
    },
    "1354524121878237365": {
      "xp": 250,
      "level": 2,
      "total_xp": 350
    }
  },
  "1407135363138588803": {
    "1079826643922722848": {
      "xp": 0,
      "level": 2,
      "total_xp": 100
    },
    "1019698414839156817": {
      "xp": 110,
      "level": 2,
      "total_xp": 210
    },
    "1491895176283553852": {
      "xp": 20,
      "level": 1,
      "total_xp": 20
    }
  },
  "1494524953653936290": {
    "1019698414839156817": {
      "xp": 110,
      "level": 2,
      "total_xp": 210
    },
    "1141232275447631932": {
      "xp": 130,
      "level": 2,
      "total_xp": 230
    }
  },
  "1493123107467038790": {
    "1365071801201463330": {
      "xp": 769,
      "level": 5,
      "total_xp": 2470
    },
    "1493100535392374994": {
      "xp": 1091,
      "level": 6,
      "total_xp": 3910
    },
    "1448123679396331694": {
      "xp": 10,
      "level": 1,
      "total_xp": 10
    },
    "1437205774853214270": {
      "xp": 10,
      "level": 1,
      "total_xp": 10
    },
    "1425265292094738686": {
      "xp": 9,
      "level": 4,
      "total_xp": 910
    }
  },
  "1374332892708343928": {
    "1288279822820184115": {
      "xp": 10,
      "level": 1,
      "total_xp": 10
    },
    "1365071801201463330": {
      "xp": 30,
      "level": 1,
      "total_xp": 30
    }
  },
  "1485790866189586604": {
    "1462308991160942675": {
      "xp": 40,
      "level": 1,
      "total_xp": 40
    },
    "1019698414839156817": {
      "xp": 10,
      "level": 1,
      "total_xp": 10
    }
  }
}